{
  "hash": "3e2ac011",
  "configHash": "30568be5",
  "lockfileHash": "abcd9c24",
  "browserHash": "add63777",
  "optimized": {
    "react": {
      "src": "../../node_modules/react/index.js",
      "file": "react.js",
      "fileHash": "8a0d85cf",
      "needsInterop": true
    },
    "react-dom/client": {
      "src": "../../node_modules/react-dom/client.js",
      "file": "react-dom_client.js",
      "fileHash": "73e62afb",
      "needsInterop": true
    },
    "axios": {
      "src": "../../node_modules/axios/index.js",
      "file": "axios.js",
      "fileHash": "eb59e9d2",
      "needsInterop": false
    },
    "keycloak-js": {
      "src": "../../node_modules/keycloak-js/dist/keycloak.mjs",
      "file": "keycloak-js.js",
      "fileHash": "fc30fa92",
      "needsInterop": false
    }
  },
  "chunks": {
    "chunk-PMYDY72F": {
      "file": "chunk-PMYDY72F.js"
    },
    "chunk-ZS7NZCD4": {
      "file": "chunk-ZS7NZCD4.js"
    }
  }
}